heas/__init__.py
heas/api.py
heas/config.py
heas/agent/__init__.py
heas/agent/base.py
heas/agent/runner.py
heas/cli/__init__.py
heas/cli/main.py
heas/evolution/__init__.py
heas/evolution/algorithms.py
heas/evolution/logging.py
heas/evolution/toolbox.py
heas/examples/__init__.py
heas/examples/hierarchy_example.py
heas/examples/simple_model.py
heas/game/__init__.py
heas/game/arena.py
heas/game/artifacts.py
heas/game/checkpoints.py
heas/game/scenarios.py
heas/game/tournament.py
heas/game/voting.py
heas/hierarchy/__init__.py
heas/hierarchy/base.py
heas/hierarchy/graph.py
heas/hierarchy/orchestrator.py
heas/schemas/genes.py
heas/schemas/mapping.py
heas/torch_integration/device.py
heas/torch_integration/params.py
heas/torch_integration/policies.py
heas/utils/io.py
heas/utils/metrics.py
heas/utils/rng.py
heas/utils/typing.py
heas/vis/__init__.py
heas/vis/evolution.py
heas/vis/hierarchy.py
heas/vis/plots.py
heas/vis/tournament.py
heas-0.2.0.dist-info/COPYING
heas-0.2.0.dist-info/LICENSE
heas-0.2.0.dist-info/METADATA
heas-0.2.0.dist-info/WHEEL
heas-0.2.0.dist-info/top_level.txt
heas-0.2.0.dist-info/RECORD
