Metadata-Version: 2.1
Name: heas
Version: 0.2.0
Summary: HEAS: Hierarchical Evolutionary Agent Simulation
Author-email: Ruiyu Zhang <ruiyuzh@connect.hku.hk>
License: LGPL-3.0-or-later
Keywords: evolutionary computation,agent-based simulation,hierarchical systems,multi-objective optimization
Classifier: Development Status :: 4 - Beta
Classifier: Intended Audience :: Science/Research
Classifier: Intended Audience :: Developers
Classifier: License :: OSI Approved :: GNU Lesser General Public License v3 (LGPLv3)
Classifier: Programming Language :: Python :: 3
Classifier: Programming Language :: Python :: 3.9
Classifier: Programming Language :: Python :: 3.10
Classifier: Programming Language :: Python :: 3.11
Classifier: Programming Language :: Python :: 3.12
Classifier: Topic :: Scientific/Engineering :: Artificial Intelligence
Classifier: Topic :: Scientific/Engineering :: Artificial Life
Classifier: Topic :: Software Development :: Libraries :: Python Modules
Requires-Python: >=3.9
License-File: LICENSE
License-File: COPYING
Requires-Dist: torch >=2.0
Requires-Dist: numpy >=1.23
Requires-Dist: pandas >=1.5
Requires-Dist: tqdm >=4.66
Requires-Dist: deap >=1.3
Requires-Dist: mesa >=2.1
Requires-Dist: matplotlib >=3.6
